llparse/C_compiler.py
llparse/__init__.py
llparse/capi_builder.py
llparse/compilator.py
llparse/constants.py
llparse/debug.py
llparse/dot.py
llparse/enumerator.py
llparse/errors.py
llparse/frontend.py
llparse/header.py
llparse/llparse.py
llparse/spanalloc.py
llparse/trie.py
llparse/_tempita/__init__.py
llparse/_tempita/__init__.pyi
llparse/_tempita/__main__.py
llparse/_tempita/_looper.py
llparse/_tempita/_looper.pyi
llparse/_tempita/compat3.py
llparse/pybuilder/__init__.py
llparse/pybuilder/builder.py
llparse/pybuilder/loopchecker.py
llparse/pybuilder/main_code.py
llparse/pybuilder/parsemap.py
llparse/pyfront/__init__.py
llparse/pyfront/code.py
llparse/pyfront/implementation.py
llparse/pyfront/namespace.py
llparse/pyfront/nodes.py
llparse/pyfront/peephole.py
llparse/pyfront/transform.py
llparse-0.3.1.dist-info/licenses/LICENSE
llparse-0.3.1.dist-info/METADATA
llparse-0.3.1.dist-info/WHEEL
llparse-0.3.1.dist-info/top_level.txt
llparse-0.3.1.dist-info/RECORD
