Metadata-Version: 2.4
Name: llparse
Version: 0.3.1
Summary: A Parody of llparse written for writing C Parsers with Python
Author-email: Vizonex <VizonexBusiness@gmail.com>
Requires-Python: >=3.10
License-File: LICENSE
Requires-Dist: typing_extensions; python_version < "3.13"
Dynamic: license-file
